{
  "semesters": [
    {
      "name": "Первый семестр",
      "courses": [
        {
          "name": "Верстка",
          "lectures": [
            {
              "title": "Основы HTML",
              "link": "/1-sem/html/1-html/index.html",
              "openDate": "2025-09-27T10:00:00",
              "order": 1,
              "homework": "https://classroom.github.com/a/PtV9F7qh",
              "homeworkDate": "2025-09-28T23:59:59"
            },
            {
              "title": "Основы CSS",
              "link": "/1-sem/html/2-css/index.html",
              "openDate": "2025-10-04T11:00:00",
              "order": 2,
              "homework": "https://classroom.github.com/a/rmQe_SPb"
            }
          ]
        },
        {
          "name": "JavaScript",
          "lectures": [
            {
              "title": "Типы данных part. 1",
              "link": "/1-sem/js/1-types-1/index.html",
              "openDate": "2025-09-27T12:30:00",
              "order": 1,
              "homework_text": "Квиз на лекции 04 октября 2025 г.",
              "homeworkDate": "2025-10-04T12:30:00"
            },
            {
              "title": "Типы данных part. 2",
              "link": "/1-sem/js/2-types/index.html",
              "openDate": "2025-10-04T12:30:00",
              "order": 2,
              "homework_text": "Ждем ссылку на GitHubClassroom"
            }
          ]
        }
      ]
    }
  ]
}
